{
  "project_id": "j302_8",
  "activities": 32,
  "resources": {
    "R1": 999999,
    "R2": 8,
    "R3": 13,
    "R4": 10
  },
  "optimization": {
    "priority_order": {
      "1": 1,
      "3": 2,
      "2": 3,
      "4": 4,
      "13": 5,
      "6": 6,
      "10": 7,
      "7": 8,
      "20": 9,
      "11": 10,
      "21": 11,
      "9": 12,
      "12": 13,
      "22": 14,
      "23": 15,
      "26": 16,
      "14": 17,
      "17": 18,
      "18": 19,
      "8": 20,
      "15": 21,
      "5": 22,
      "27": 23,
      "16": 24,
      "29": 25,
      "24": 26,
      "19": 27,
      "25": 28,
      "28": 29,
      "30": 30,
      "31": 31,
      "32": 32
    },
    "start_times": {
      "1": 0,
      "3": 0,
      "2": 0,
      "4": 9,
      "13": 9,
      "6": 3,
      "10": 9,
      "7": 9,
      "20": 9,
      "11": 3,
      "21": 12,
      "9": 18,
      "12": 28,
      "22": 18,
      "23": 35,
      "26": 41,
      "14": 10,
      "17": 14,
      "18": 35,
      "8": 18,
      "15": 12,
      "5": 41,
      "27": 41,
      "16": 28,
      "29": 37,
      "24": 28,
      "19": 47,
      "25": 37,
      "28": 49,
      "30": 54,
      "31": 51,
      "32": 57
    },
    "total_duration": 57,
    "robustness": 31.663062789035095,
    "global_resources_request": 14,
    "project": {
      "project_id": "temp",
      "local_resources": {
        "R1": 999999,
        "R2": 8,
        "R3": 13,
        "R4": 10
      },
      "successors": [],
      "predecessors": [],
      "activities": {
        "1": {
          "activity_id": 1,
          "duration": 0,
          "resource_request": {
            "R1": 0,
            "R2": 0,
            "R3": 0,
            "R4": 0
          },
          "predecessors": [],
          "successors": [
            2,
            3,
            4
          ]
        },
        "2": {
          "activity_id": 2,
          "duration": 9,
          "resource_request": {
            "R1": 0,
            "R2": 0,
            "R3": 8,
            "R4": 0
          },
          "predecessors": [
            1
          ],
          "successors": [
            13,
            19,
            20
          ]
        },
        "3": {
          "activity_id": 3,
          "duration": 3,
          "resource_request": {
            "R1": 1,
            "R2": 0,
            "R3": 0,
            "R4": 0
          },
          "predecessors": [
            1
          ],
          "successors": [
            5,
            6,
            11
          ]
        },
        "4": {
          "activity_id": 4,
          "duration": 3,
          "resource_request": {
            "R1": 0,
            "R2": 0,
            "R3": 8,
            "R4": 0
          },
          "predecessors": [
            1
          ],
          "successors": [
            15,
            21,
            25
          ]
        },
        "5": {
          "activity_id": 5,
          "duration": 6,
          "resource_request": {
            "R1": 0,
            "R2": 0,
            "R3": 0,
            "R4": 8
          },
          "predecessors": [
            3
          ],
          "successors": [
            19,
            31
          ]
        },
        "6": {
          "activity_id": 6,
          "duration": 6,
          "resource_request": {
            "R1": 0,
            "R2": 0,
            "R3": 0,
            "R4": 2
          },
          "predecessors": [
            3
          ],
          "successors": [
            7,
            10
          ]
        },
        "7": {
          "activity_id": 7,
          "duration": 9,
          "resource_request": {
            "R1": 0,
            "R2": 0,
            "R3": 0,
            "R4": 3
          },
          "predecessors": [
            6
          ],
          "successors": [
            8,
            9,
            22
          ]
        },
        "8": {
          "activity_id": 8,
          "duration": 7,
          "resource_request": {
            "R1": 0,
            "R2": 0,
            "R3": 0,
            "R4": 8
          },
          "predecessors": [
            7
          ],
          "successors": [
            16
          ]
        },
        "9": {
          "activity_id": 9,
          "duration": 10,
          "resource_request": {
            "R1": 0,
            "R2": 0,
            "R3": 0,
            "R4": 2
          },
          "predecessors": [
            7
          ],
          "successors": [
            12,
            16,
            24
          ]
        },
        "10": {
          "activity_id": 10,
          "duration": 1,
          "resource_request": {
            "R1": 1,
            "R2": 0,
            "R3": 0,
            "R4": 0
          },
          "predecessors": [
            6
          ],
          "successors": [
            14,
            26
          ]
        },
        "11": {
          "activity_id": 11,
          "duration": 8,
          "resource_request": {
            "R1": 0,
            "R2": 0,
            "R3": 0,
            "R4": 2
          },
          "predecessors": [
            3
          ],
          "successors": [
            30
          ]
        },
        "12": {
          "activity_id": 12,
          "duration": 7,
          "resource_request": {
            "R1": 0,
            "R2": 0,
            "R3": 0,
            "R4": 8
          },
          "predecessors": [
            9
          ],
          "successors": [
            18
          ]
        },
        "13": {
          "activity_id": 13,
          "duration": 5,
          "resource_request": {
            "R1": 9,
            "R2": 0,
            "R3": 0,
            "R4": 0
          },
          "predecessors": [
            2
          ],
          "successors": [
            24
          ]
        },
        "14": {
          "activity_id": 14,
          "duration": 4,
          "resource_request": {
            "R1": 0,
            "R2": 0,
            "R3": 0,
            "R4": 1
          },
          "predecessors": [
            10
          ],
          "successors": [
            17
          ]
        },
        "15": {
          "activity_id": 15,
          "duration": 7,
          "resource_request": {
            "R1": 0,
            "R2": 1,
            "R3": 0,
            "R4": 0
          },
          "predecessors": [
            4
          ],
          "successors": [
            29
          ]
        },
        "16": {
          "activity_id": 16,
          "duration": 9,
          "resource_request": {
            "R1": 0,
            "R2": 4,
            "R3": 0,
            "R4": 0
          },
          "predecessors": [
            8,
            9
          ],
          "successors": [
            29
          ]
        },
        "17": {
          "activity_id": 17,
          "duration": 4,
          "resource_request": {
            "R1": 0,
            "R2": 5,
            "R3": 0,
            "R4": 0
          },
          "predecessors": [
            14
          ],
          "successors": [
            28,
            29
          ]
        },
        "18": {
          "activity_id": 18,
          "duration": 2,
          "resource_request": {
            "R1": 0,
            "R2": 0,
            "R3": 9,
            "R4": 0
          },
          "predecessors": [
            12
          ],
          "successors": [
            25
          ]
        },
        "19": {
          "activity_id": 19,
          "duration": 2,
          "resource_request": {
            "R1": 0,
            "R2": 2,
            "R3": 0,
            "R4": 0
          },
          "predecessors": [
            2,
            5
          ],
          "successors": [
            28
          ]
        },
        "20": {
          "activity_id": 20,
          "duration": 2,
          "resource_request": {
            "R1": 0,
            "R2": 0,
            "R3": 0,
            "R4": 2
          },
          "predecessors": [
            2
          ],
          "successors": [
            26
          ]
        },
        "21": {
          "activity_id": 21,
          "duration": 7,
          "resource_request": {
            "R1": 0,
            "R2": 0,
            "R3": 7,
            "R4": 0
          },
          "predecessors": [
            4
          ],
          "successors": [
            27
          ]
        },
        "22": {
          "activity_id": 22,
          "duration": 8,
          "resource_request": {
            "R1": 0,
            "R2": 4,
            "R3": 0,
            "R4": 0
          },
          "predecessors": [
            7
          ],
          "successors": [
            23
          ]
        },
        "23": {
          "activity_id": 23,
          "duration": 6,
          "resource_request": {
            "R1": 0,
            "R2": 0,
            "R3": 0,
            "R4": 3
          },
          "predecessors": [
            22
          ],
          "successors": [
            26,
            27
          ]
        },
        "24": {
          "activity_id": 24,
          "duration": 1,
          "resource_request": {
            "R1": 0,
            "R2": 0,
            "R3": 2,
            "R4": 0
          },
          "predecessors": [
            9,
            13
          ],
          "successors": [
            25
          ]
        },
        "25": {
          "activity_id": 25,
          "duration": 5,
          "resource_request": {
            "R1": 0,
            "R2": 0,
            "R3": 6,
            "R4": 0
          },
          "predecessors": [
            4,
            18,
            24
          ],
          "successors": [
            28
          ]
        },
        "26": {
          "activity_id": 26,
          "duration": 10,
          "resource_request": {
            "R1": 0,
            "R2": 5,
            "R3": 0,
            "R4": 0
          },
          "predecessors": [
            10,
            20,
            23
          ],
          "successors": [
            30
          ]
        },
        "27": {
          "activity_id": 27,
          "duration": 10,
          "resource_request": {
            "R1": 10,
            "R2": 0,
            "R3": 0,
            "R4": 0
          },
          "predecessors": [
            21,
            23
          ],
          "successors": [
            31
          ]
        },
        "28": {
          "activity_id": 28,
          "duration": 5,
          "resource_request": {
            "R1": 4,
            "R2": 0,
            "R3": 0,
            "R4": 0
          },
          "predecessors": [
            17,
            19,
            25
          ],
          "successors": [
            30
          ]
        },
        "29": {
          "activity_id": 29,
          "duration": 1,
          "resource_request": {
            "R1": 4,
            "R2": 0,
            "R3": 0,
            "R4": 0
          },
          "predecessors": [
            15,
            16,
            17
          ],
          "successors": [
            32
          ]
        },
        "30": {
          "activity_id": 30,
          "duration": 3,
          "resource_request": {
            "R1": 0,
            "R2": 7,
            "R3": 0,
            "R4": 0
          },
          "predecessors": [
            11,
            26,
            28
          ],
          "successors": [
            32
          ]
        },
        "31": {
          "activity_id": 31,
          "duration": 4,
          "resource_request": {
            "R1": 10,
            "R2": 0,
            "R3": 0,
            "R4": 0
          },
          "predecessors": [
            5,
            27
          ],
          "successors": [
            32
          ]
        },
        "32": {
          "activity_id": 32,
          "duration": 0,
          "resource_request": {
            "R1": 0,
            "R2": 0,
            "R3": 0,
            "R4": 0
          },
          "predecessors": [
            29,
            30,
            31
          ],
          "successors": []
        }
      },
      "start_time": null,
      "weight": 1
    }
  }
}